MANIFEST.in
README.rst
setup.py
corenlpy/README.md
corenlpy/SETTINGS.py
corenlpy/__init__.py
corenlpy/run_corenlp.py
corenlpy/test.py
corenlpy.egg-info/PKG-INFO
corenlpy.egg-info/SOURCES.txt
corenlpy.egg-info/dependency_links.txt
corenlpy.egg-info/requires.txt
corenlpy.egg-info/top_level.txt
corenlpy/data/AIDA/9fd040220089f78d.txt.json
corenlpy/data/AIDA/b670037f5942445d.txt.json
corenlpy/data/AIDA/b67006685423d856.txt.json
corenlpy/data/AIDA/b6700b413f16cd8f.txt.json
corenlpy/data/AIDA/b6700d50238b23dd.txt.json
corenlpy/data/AIDA/b670173bb02bc017.txt.json
corenlpy/data/AIDA/b67018fd9a0536ae.txt.json
corenlpy/data/AIDA/b67027bb45a91ee4.txt.json
corenlpy/data/AIDA/b67029d77360753c.txt.json
corenlpy/data/AIDA/b67029f45f2e6e03.txt.json
corenlpy/data/AIDA/b6702ab21fda2925.txt.json
corenlpy/data/AIDA/b671489a0ff0e6c4.txt.json
corenlpy/data/CoreNLP/.b6752ee2ad55ccab.txt.xml.swp
corenlpy/data/CoreNLP/9fd040220089f78d.txt.xml
corenlpy/data/CoreNLP/b670037f5942445d.txt.xml
corenlpy/data/CoreNLP/b67006685423d856.txt.xml
corenlpy/data/CoreNLP/b6700b413f16cd8f.txt.xml
corenlpy/data/CoreNLP/b6700d50238b23dd.txt.xml
corenlpy/data/CoreNLP/b670173bb02bc017.txt.xml
corenlpy/data/CoreNLP/b67018fd9a0536ae.txt.xml
corenlpy/data/CoreNLP/b67027bb45a91ee4.txt.xml
corenlpy/data/CoreNLP/b67029d77360753c.txt.xml
corenlpy/data/CoreNLP/b67029f45f2e6e03.txt.xml
corenlpy/data/CoreNLP/b6702ab21fda2925.txt.xml
corenlpy/data/CoreNLP/b671489a0ff0e6c4.txt.xml
corenlpy/data/raw-text/b670037f5942445d.txt
corenlpy/data/raw-text/b67006685423d856.txt
corenlpy/data/raw-text/b6700b413f16cd8f.txt
corenlpy/data/raw-text/b6700d50238b23dd.txt
corenlpy/data/raw-text/b670173bb02bc017.txt
corenlpy/data/raw-text/b67018fd9a0536ae.txt
corenlpy/data/raw-text/b67027bb45a91ee4.txt
corenlpy/data/raw-text/b67029d77360753c.txt
corenlpy/data/raw-text/b67029f45f2e6e03.txt
corenlpy/data/raw-text/b6702ab21fda2925.txt
corenlpy/data/raw-text/b671489a0ff0e6c4.txt