Metadata-Version: 1.1
Name: corenlpy
Version: 0.0.5
Summary: Work with CoreNLP in Python
Home-page: https://github.com/enewe101/corenlpy
Author: Edward Newell
Author-email: edward.newell@gmail.com
License: MIT
Keywords: NLP natrual language processing computational linguistics CoreNLP Stanford parser
Platform: UNKNOWN
Classifier: Development Status :: 3 - Alpha
Classifier: Intended Audience :: Developers
Classifier: Topic :: Software Development :: Build Tools
Classifier: License :: OSI Approved :: MIT License
Classifier: Programming Language :: Python :: 2.7
